Live/__init__.py
Live/py.typed
Live/Application/__init__.py
Live/Application/py.typed
Live/Base/__init__.py
Live/Base/py.typed
Live/Browser/__init__.py
Live/Browser/py.typed
Live/CcControlDevice/__init__.py
Live/CcControlDevice/py.typed
Live/Chain/__init__.py
Live/Chain/py.typed
Live/ChainMixerDevice/__init__.py
Live/ChainMixerDevice/py.typed
Live/Clip/__init__.py
Live/Clip/py.typed
Live/ClipSlot/__init__.py
Live/ClipSlot/py.typed
Live/CompressorDevice/__init__.py
Live/CompressorDevice/py.typed
Live/Conversions/__init__.py
Live/Conversions/py.typed
Live/Device/__init__.py
Live/Device/py.typed
Live/DeviceIO/__init__.py
Live/DeviceIO/py.typed
Live/DeviceParameter/__init__.py
Live/DeviceParameter/py.typed
Live/DriftDevice/__init__.py
Live/DriftDevice/py.typed
Live/DrumChain/__init__.py
Live/DrumChain/py.typed
Live/DrumPad/__init__.py
Live/DrumPad/py.typed
Live/Eq8Device/__init__.py
Live/Eq8Device/py.typed
Live/Groove/__init__.py
Live/Groove/py.typed
Live/GroovePool/__init__.py
Live/GroovePool/py.typed
Live/HybridReverbDevice/__init__.py
Live/HybridReverbDevice/py.typed
Live/Listener/__init__.py
Live/Listener/py.typed
Live/LomObject/__init__.py
Live/LomObject/py.typed
Live/MaxDevice/__init__.py
Live/MaxDevice/py.typed
Live/MeldDevice/__init__.py
Live/MeldDevice/py.typed
Live/MidiMap/__init__.py
Live/MidiMap/py.typed
Live/MixerDevice/__init__.py
Live/MixerDevice/py.typed
Live/PluginDevice/__init__.py
Live/PluginDevice/py.typed
Live/RackDevice/__init__.py
Live/RackDevice/py.typed
Live/RoarDevice/__init__.py
Live/RoarDevice/py.typed
Live/Sample/__init__.py
Live/Sample/py.typed
Live/Scene/__init__.py
Live/Scene/py.typed
Live/ShifterDevice/__init__.py
Live/ShifterDevice/py.typed
Live/SimplerDevice/__init__.py
Live/SimplerDevice/py.typed
Live/Song/__init__.py
Live/Song/py.typed
Live/SpectralResonatorDevice/__init__.py
Live/SpectralResonatorDevice/py.typed
Live/Track/__init__.py
Live/Track/py.typed
Live/WavetableDevice/__init__.py
Live/WavetableDevice/py.typed
ableton_control_surface_core-0.0.7.dist-info/METADATA
ableton_control_surface_core-0.0.7.dist-info/WHEEL
ableton_control_surface_core-0.0.7.dist-info/py.typed
ableton_control_surface_core-0.0.7.dist-info/top_level.txt
ableton_control_surface_core-0.0.7.dist-info/RECORD
